pychi/__init__.py
pychi/light.py
pychi/materials.py
pychi/models.py
pychi/solvers.py
pychi/utils.py
pychi-0.0.20.dist-info/licenses/LICENSE
pychi-0.0.20.dist-info/METADATA
pychi-0.0.20.dist-info/WHEEL
pychi-0.0.20.dist-info/top_level.txt
pychi-0.0.20.dist-info/RECORD
