Metadata-Version: 2.4
Name: pychi
Version: 0.0.20
Summary: Simulation package for the propagation of optical pulses in nonlinear media
Author-email: Ultrafast Microphotonics Group - DESY <pychi@desy.de>
Project-URL: Homepage, https://github.com/pychi-code/pychi
Project-URL: Documentation, https://pychi.readthedocs.io/en/latest/index.html
Project-URL: PyPI, https://pypi.org/project/pychi/
Classifier: Programming Language :: Python :: 3
Classifier: License :: OSI Approved :: MIT License
Classifier: Operating System :: OS Independent
Requires-Python: >=3.7
License-File: LICENSE
Requires-Dist: matplotlib>=3.1.3
Requires-Dist: numpy>=1.21.6
Requires-Dist: scipy>=1.4.1
Requires-Dist: numba>=0.56.0
Requires-Dist: pyFFTW>=0.12.0
Dynamic: license-file
